{
  "version": "7",
  "dialect": "mysql",
  "entries": [
    {
      "idx": 0,
      "version": "5",
      "when": 1745766587800,
      "tag": "0000_legal_tag",
      "breakpoints": true
    },
    {
      "idx": 1,
      "version": "5",
      "when": 1746546225092,
      "tag": "0001_friendly_mister_fear",
      "breakpoints": true
    },
    {
      "idx": 2,
      "version": "5",
      "when": 1746546548705,
      "tag": "0002_thin_squadron_sinister",
      "breakpoints": true
    },
    {
      "idx": 3,
      "version": "5",
      "when": 1746547043146,
      "tag": "0003_equal_iceman",
      "breakpoints": true
    },
    {
      "idx": 4,
      "version": "5",
      "when": 1746848829672,
      "tag": "0004_colossal_lady_deathstrike",
      "breakpoints": true
    },
    {
      "idx": 5,
      "version": "5",
      "when": 1746848969091,
      "tag": "0005_friendly_sasquatch",
      "breakpoints": true
    }
  ]
}